djitellopy_reduced/__init__.py
djitellopy_reduced/enforce_types.py
djitellopy_reduced/swarm.py
djitellopy_reduced/tello.py
djitellopy_reduced-2.4.0.dist-info/LICENSE.txt
djitellopy_reduced-2.4.0.dist-info/METADATA
djitellopy_reduced-2.4.0.dist-info/WHEEL
djitellopy_reduced-2.4.0.dist-info/RECORD
